openbase/__init__.py
openbase/__main__.py
openbase/_version.py
openbase/coder/__init__.py
openbase/coder/admin.py
openbase/coder/apps.py
openbase/coder/consumers.py
openbase/coder/middleware.py
openbase/coder/models.py
openbase/coder/routing.py
openbase/coder/serializers.py
openbase/coder/urls.py
openbase/coder/views.py
openbase/coder/migrations/0001_initial.py
openbase/coder/migrations/__init__.py
openbase/config/__init__.py
openbase/config/asgi.py
openbase/config/authentication.py
openbase/config/managers.py
openbase/config/serializers.py
openbase/config/settings.py
openbase/config/urls.py
openbase/config/views.py
openbase/config/viewsets.py
openbase/config/wsgi.py
openbase/core/__init__.py
openbase/core/claude_code_helper.py
openbase/core/default_env.py
openbase/core/errors.py
openbase/core/git_helpers.py
openbase/core/parsing.py
openbase/core/parsing_utils.py
openbase/core/paths.py
openbase/core/project_config.py
openbase/core/project_scaffolder.py
openbase/core/pyright_config.py
openbase/core/pyright_settings.py
openbase/core/sourcemapped_dataclass.py
openbase/core/template_manager.py
openbase/core/utils.py
openbase/core/cli/__init__.py
openbase/core/cli/cli.py
openbase/core/cli/default.py
openbase/core/cli/generate.py
openbase/core/cli/generate_backend.py
openbase/core/cli/generate_frontend.py
openbase/core/cli/generate_schema.py
openbase/core/cli/generation_command.py
openbase/core/cli/init.py
openbase/core/cli/server.py
openbase/core/cli/utils.py
openbase/core/cli/watcher.py
openbase/entrypoint/.gitkeep
openbase/entrypoint/manage.py
openbase/manage_commands/__init__.py
openbase/manage_commands/apps.py
openbase/manage_commands/asgi.py
openbase/manage_commands/models.py
openbase/manage_commands/parsing.py
openbase/manage_commands/serializers.py
openbase/manage_commands/urls.py
openbase/manage_commands/views.py
openbase/models/__init__.py
openbase/models/apps.py
openbase/models/asgi.py
openbase/models/models.py
openbase/models/parsing.py
openbase-1.2.1.dist-info/METADATA
openbase-1.2.1.dist-info/WHEEL
openbase-1.2.1.dist-info/entry_points.txt
openbase-1.2.1.dist-info/RECORD
