Metadata-Version: 2.4
Name: openbase
Version: 1.2.1
Summary: Openbase Django Meta-Server
Author-email: Gabe Montague <gabemontague@outlook.com>
Requires-Dist: boilersync
Requires-Dist: channels-redis==4.3.0
Requires-Dist: channels==4.3.1
Requires-Dist: click==8.2.1
Requires-Dist: django-cors-headers==4.8.0
Requires-Dist: django==5.2.6
Requires-Dist: djangorestframework-dataclasses==1.4.0
Requires-Dist: djangorestframework==3.16.1
Requires-Dist: gunicorn==23.0.0
Requires-Dist: multi-workspace
Requires-Dist: python-dotenv==1.1.1
Requires-Dist: requests==2.32.5
Requires-Dist: uvicorn==0.35.0
Requires-Dist: watchdog==6.0.0
Requires-Dist: whitenoise==6.10.0
Provides-Extra: dev
Requires-Dist: pytest==8.4.2; extra == 'dev'
